contourplots/__init__.py
contourplots/utils.py
contourplots-0.3.4.dist-info/LICENSE.txt
contourplots-0.3.4.dist-info/METADATA
contourplots-0.3.4.dist-info/WHEEL
contourplots-0.3.4.dist-info/top_level.txt
contourplots-0.3.4.dist-info/RECORD
