Metadata-Version: 2.1
Name: contourplots
Version: 0.3.4
Summary: A toolkit for generating multi-dimensional plots easily, usefully, and legibly.
Home-page: https://github.com/sarangbhagwat/contourplots
Author: Sarang S. Bhagwat
Author-email: sarang.bhagwat.git@gmail.com
License: MIT
Classifier: Development Status :: 3 - Alpha
Classifier: Intended Audience :: Science/Research
Classifier: License :: OSI Approved :: University of Illinois/NCSA Open Source License
Classifier: Operating System :: Microsoft :: Windows
Classifier: Programming Language :: Python :: 3.9
License-File: LICENSE.txt
Requires-Dist: matplotlib (==3.5.2)
Requires-Dist: numpy (>=1.23.4)
Requires-Dist: imageio (>=2.19.3)
